mcctl/__config__.py
mcctl/__init__.py
mcctl/__main__.py
mcctl/common.py
mcctl/config.py
mcctl/perms.py
mcctl/plugin.py
mcctl/proc.py
mcctl/service.py
mcctl/status.py
mcctl/storage.py
mcctl/visuals.py
mcctl/web.py
mcctl-0.4.3.dist-info/LICENSE
mcctl-0.4.3.dist-info/METADATA
mcctl-0.4.3.dist-info/WHEEL
mcctl-0.4.3.dist-info/entry_points.txt
mcctl-0.4.3.dist-info/top_level.txt
mcctl-0.4.3.dist-info/RECORD
