Metadata-Version: 2.1
Name: mcctl
Version: 0.4.3
Summary: Manage, configure, and create multiple Minecraft servers easily with a command-line interface.
Home-page: https://github.com/DaTurret/mcctl
Author: DaTurret
Author-email: mattcott14@hotmail.com
License: gpl-3.0
Platform: UNKNOWN
Classifier: Development Status :: 3 - Alpha
Classifier: License :: OSI Approved :: GNU General Public License v3 (GPLv3)
Classifier: Programming Language :: Python :: 3
Classifier: Programming Language :: Python :: 3.8
Classifier: Programming Language :: Python :: 3.9
Classifier: Environment :: Console
Classifier: Operating System :: POSIX :: Linux
Requires-Python: >=3.8
License-File: LICENSE
Requires-Dist: mcstatus (<7.0.0,>=6.0.1)
Requires-Dist: requests (<3.0.0,>=2.25.0)
Requires-Dist: pystemd
